Metadata-Version: 1.1
Name: amineparser
Version: 0.0.8
Summary: Resume parser for french and english resumes
Home-page: UNKNOWN
Author: Mohamed Amine Bouslimi
Author-email: aminobouslimi@gmail.com
License: MIT
Keywords: CVParser
Platform: UNKNOWN
Classifier: Development Status :: 5 - Production/Stable
Classifier: Intended Audience :: Education
Classifier: Operating System :: Microsoft :: Windows :: Windows 10
Classifier: License :: OSI Approved :: MIT License
Classifier: Programming Language :: Python :: 3
